streamlit_grid/__init__.py
streamlit_grid/example.py
streamlit_grid/frontend/build/asset-manifest.json
streamlit_grid/frontend/build/bootstrap.min.css
streamlit_grid/frontend/build/index.html
streamlit_grid/frontend/build/static/css/main.450e7e2d.css
streamlit_grid/frontend/build/static/css/main.450e7e2d.css.map
streamlit_grid/frontend/build/static/js/main.78669b6c.js
streamlit_grid/frontend/build/static/js/main.78669b6c.js.LICENSE.txt
streamlit_grid/frontend/build/static/js/main.78669b6c.js.map
streamlit_grid-0.1.2.dist-info/licenses/LICENSE
streamlit_grid-0.1.2.dist-info/METADATA
streamlit_grid-0.1.2.dist-info/WHEEL
streamlit_grid-0.1.2.dist-info/top_level.txt
streamlit_grid-0.1.2.dist-info/RECORD
